{
	"credit": "Made by Miffen Kop!",
	"texture_size": [1000, 320],
	"textures": {
		"1": "minecraft-wiki:flat"
	},
	"elements": [
		{
			"from": [-6, 20, -2],
			"to": [2, 40, 2],
			"rotation": {"angle": 0, "axis": "y", "origin": [-8, 0, -10]},
			"faces": {
				"north": {"uv": [10.048, 0.4, 10.176, 1.4], "texture": "#1"},
				"east": {"uv": [9.664, 0.4, 9.728, 1.4], "texture": "#1"},
				"west": {"uv": [10.176, 0.4, 10.24, 1.4], "texture": "#1"},
				"up": {"uv": [10.176, 0.2, 10.048, 0], "texture": "#1"},
				"down": {"uv": [10.176, 2.4, 10.048, 2.2], "texture": "#1"}
			}
		},
		{
			"from": [14, 4, -2],
			"to": [22, 44, 2],
			"rotation": {"angle": 0, "axis": "y", "origin": [-8, 0, -10]},
			"faces": {
				"north": {"uv": [9.728, 0.2, 9.856, 2.2], "texture": "#1"},
				"east": {"uv": [9.664, 0.2, 9.728, 2.2], "texture": "#1"},
				"west": {"uv": [10.176, 0.2, 10.24, 2.2], "texture": "#1"},
				"up": {"uv": [9.856, 0.2, 9.728, 0], "texture": "#1"},
				"down": {"uv": [9.856, 2.4, 9.728, 2.2], "texture": "#1"}
			}
		},
		{
			"from": [-2, 36, -2],
			"to": [14, 44, 2],
			"rotation": {"angle": 0, "axis": "y", "origin": [-8, 0, -10]},
			"faces": {
				"north": {"uv": [9.856, 0.2, 10.112, 0.6], "texture": "#1"},
				"west": {"uv": [10.176, 0.2, 10.24, 0.6], "texture": "#1"},
				"up": {"uv": [10.112, 0.2, 9.856, 0], "texture": "#1"},
				"down": {"uv": [10.112, 2.4, 9.856, 2.2], "texture": "#1"}
			}
		},
		{
			"from": [-2, 16, -2],
			"to": [14, 24, 2],
			"rotation": {"angle": 0, "axis": "y", "origin": [-8, 0, -10]},
			"faces": {
				"north": {"uv": [9.856, 1.2, 10.112, 1.6], "texture": "#1"},
				"west": {"uv": [10.176, 1.2, 10.24, 1.6], "texture": "#1"},
				"up": {"uv": [10.112, 0.2, 9.856, 0], "texture": "#1"},
				"down": {"uv": [10.112, 2.4, 9.856, 2.2], "texture": "#1"}
			}
		},
		{
			"from": [22, 0, 2],
			"to": [26, 48, 18],
			"rotation": {"angle": 0, "axis": "y", "origin": [-8, 0, -10]},
			"faces": {
				"north": {"uv": [0.784, 14.4, 0.816, 15.6], "texture": "#1"},
				"east": {"uv": [0.656, 14.4, 0.784, 15.6], "texture": "#1"},
				"south": {"uv": [0.816, 14.4, 0.784, 15.6], "texture": "#1"},
				"up": {"uv": [0.816, 14.4, 0.784, 14], "texture": "#1"},
				"down": {"uv": [0.816, 16, 0.784, 15.6], "texture": "#1"}
			}
		},
		{
			"from": [-6, 12, 2],
			"to": [22, 48, 18],
			"rotation": {"angle": 0, "axis": "y", "origin": [-8, 0, -10]},
			"faces": {
				"north": {"uv": [0.208, 14.4, 0.432, 15.3], "texture": "#1"},
				"south": {"uv": [0.432, 14.4, 0.208, 15.3], "texture": "#1"},
				"west": {"uv": [0.512, 14.4, 0.64, 15.3], "texture": "#1"},
				"up": {"uv": [0.432, 14.4, 0.208, 14], "texture": "#1"},
				"down": {"uv": [0.432, 16, 0.208, 15.6], "texture": "#1"}
			}
		},
		{
			"from": [10, 0, 2],
			"to": [22, 12, 18],
			"rotation": {"angle": 0, "axis": "y", "origin": [-8, 0, -10]},
			"faces": {
				"north": {"uv": [0.208, 15.3, 0.304, 15.6], "texture": "#1"},
				"south": {"uv": [0.304, 15.3, 0.208, 15.6], "texture": "#1"},
				"west": {"uv": [0.512, 15.3, 0.64, 15.6], "texture": "#1"},
				"down": {"uv": [0.304, 16, 0.208, 15.6], "texture": "#1"}
			}
		},
		{
			"from": [-10, 16, 2],
			"to": [-6, 44, 18],
			"rotation": {"angle": 0, "axis": "y", "origin": [-8, 0, -10]},
			"faces": {
				"north": {"uv": [0.784, 14.5, 0.816, 15.2], "texture": "#1"},
				"south": {"uv": [0.816, 14.5, 0.784, 15.2], "texture": "#1"},
				"west": {"uv": [0.816, 14.5, 0.944, 15.2], "texture": "#1"},
				"up": {"uv": [0.816, 14.4, 0.784, 14], "texture": "#1"},
				"down": {"uv": [0.816, 16, 0.784, 15.6], "texture": "#1"}
			}
		}
	]
}